yahoo_fb_stat_analysis/__init__.py
yahoo_fb_stat_analysis/main.py
yahoo_fb_stat_analysis-6.0.1.dist-info/LICENSE.txt
yahoo_fb_stat_analysis-6.0.1.dist-info/METADATA
yahoo_fb_stat_analysis-6.0.1.dist-info/WHEEL
yahoo_fb_stat_analysis-6.0.1.dist-info/top_level.txt
yahoo_fb_stat_analysis-6.0.1.dist-info/RECORD
