Metadata-Version: 2.1
Name: yahoo-fb-stat-analysis
Version: 6.0.1
Summary: Python module to allow for advanced statistical analysis
Home-page: https://github.com/KipFeher85/Fantasy-Baseball
Author: Kip Feher
Author-email: kipfeher85@gmail.com
License: MIT
Classifier: License :: OSI Approved :: MIT License
Classifier: Programming Language :: Python :: 3.9
License-File: LICENSE.txt
Requires-Dist: yahoo-oauth
Requires-Dist: yahoo-fantasy-api
Requires-Dist: MLB-StatsAPI
Requires-Dist: pandas
Requires-Dist: datetime
Requires-Dist: lxml
Requires-Dist: python-dateutil
Requires-Dist: setuptools
Requires-Dist: requests
Requires-Dist: pip
Requires-Dist: PyYAML
